grdtiler/__init__.py
grdtiler/_version.py
grdtiler/get-pip.py
grdtiler/grdtiler.py
grdtiler/tools.py
tests/__init__.py
tests/test_grdtiler.py
grdtiler-0.0.4.dist-info/LICENSE
grdtiler-0.0.4.dist-info/METADATA
grdtiler-0.0.4.dist-info/WHEEL
grdtiler-0.0.4.dist-info/top_level.txt
grdtiler-0.0.4.dist-info/RECORD
