Metadata-Version: 2.1
Name: grdtiler
Version: 0.0.4
Summary: A package for tilling GRD products
Author: jean2262
Author-email: jean-renaud.miadana@oceanscope.com
Classifier: Programming Language :: Python :: 3
Classifier: License :: OSI Approved :: MIT License
Classifier: Operating System :: OS Independent
Requires-Python: >=3.10
License-File: LICENSE
Requires-Dist: numpy
Requires-Dist: pytest
Requires-Dist: pytest-cov
Requires-Dist: tqdm
Requires-Dist: shapely
Requires-Dist: xarray
Requires-Dist: xsar
Requires-Dist: xarray-safe-s1
Requires-Dist: xradarsat2
Requires-Dist: xarray-safe-rcm
Requires-Dist: xsarsea
